[{
    "tag": "div",
    "props": {
        "id": "aboutMe_Resume_Box"
    },
    "lang": "",
    "children": [{
        "tag": "div",
        "props": {
            "id": "aboutMe_Resume_Header"
        },
        "lang": "",
        "children": [{
            "tag": "p",
            "props": {},
            "lang": "",
            "children": ["LEE SEE CHEN"]
        }, {
            "tag": "div",
            "props": {},
            "lang": "",
            "children": [{
                "tag": "p",
                "props": {},
                "lang": "",
                "children": [{
                    "tag": "a",
                    "props": {
                        "target": "_blank",
                        "href": "mailto:leeseechen@gmail.com"
                    },
                    "lang": "",
                    "children": ["leeseechen@gmail.com"]
                }]
            }]
        }]
    }, {
       "tag": "div",
        "props": {
            "id": "aboutMe_Resume_Content"
        },
        "lang": "",
        "children": [{
            "tag": "div",
            "props": {
                "class": "aboutMe_Resume_Session"
            },
            "lang": "",
            "children": [{
                "tag": "p",
                "props": {
                    "class": "aboutMe_Resume_Session_Title"
                },
                "lang": "about",
                "children": ["_aboutMe_Resume_Session_Education_"]
            }, {
                "tag": "div",
                "props": {
                    "id": "aboutMe_Resume_Education_Area"
                },
                "lang": "",
                "children": [{
                    "tag": "p",
                    "props": {
                        "class": "aboutMe_Resume_Session_Topic_Title"
                    },
                    "lang": "about",
                    "children": ["_aboutMe_Resume_Education_Header_Title_"]
                }, {
                    "tag": "p",
                    "props": {},
                    "lang": "about",
                    "children": ["_aboutMe_Resume_Education_Header_School_"]
                }, {
                    "tag": "p",
                    "props": {},
                    "lang": "about",
                    "children": ["_aboutMe_Resume_Education_Header_Graduation_"]
                }]
            }, {
                "tag": "div",
                "props": {
                    "id": "aboutMe_Resume_Education_Area_2"
                },
                "lang": "",
                "children": [{
                    "tag": "p",
                    "props": {
                        "class": "aboutMe_Resume_Session_Title_2"
                    },
                    "lang": "about",
                    "children": ["_aboutMe_Resume_Education_Courses_"]
                }, {
                    "tag": "ol",
                    "props": {},
                    "lang": "",
                    "children": [{
                        "tag": "li",
                        "props": {},
                        "lang": "about",
                        "children": ["_aboutMe_Resume_Education_Courses_DataStructure_"]
                    }, {
                        "tag": "li",
                        "props": {},
                        "lang": "about",
                        "children": ["_aboutMe_Resume_Education_Courses_OOP_"]
                    }, {
                        "tag": "li",
                        "props": {},
                        "lang": "about",
                        "children": ["_aboutMe_Resume_Education_Courses_Java_"]
                    }, {
                        "tag": "li",
                        "props": {},
                        "lang": "about",
                        "children": ["_aboutMe_Resume_Education_Courses_Python_"]
                    }, {
                        "tag": "li",
                        "props": {},
                        "lang": "about",
                        "children": ["_aboutMe_Resume_Education_Courses_C_"]
                    }, {
                        "tag": "li",
                        "props": {},
                        "lang": "about",
                        "children": ["_aboutMe_Resume_Education_Courses_Web_"]
                    }, {
                        "tag": "li",
                        "props": {},
                        "lang": "about",
                        "children": ["_aboutMe_Resume_Education_Courses_BigDataAnalysis_"]
                    }, {
                        "tag": "li",
                        "props": {},
                        "lang": "about",
                        "children": ["_aboutMe_Resume_Education_Courses_SystemDesign_"]
                    }, {
                        "tag": "li",
                        "props": {},
                        "lang": "about",
                        "children": ["_aboutMe_Resume_Education_Courses_Database_"]
                    }]
                }, {
                    "tag": "p",
                    "props": {
                        "class": "aboutMe_Resume_Session_Title_2"
                    },
                    "lang": "about",
                    "children": ["_aboutMe_Resume_Education_Honor_"]
                }, {
                    "tag": "ol",
                    "props": {},
                    "lang": "",
                    "children": [{
                        "tag": "li",
                        "props": {},
                        "lang": "about",
                        "children": ["_aboutMe_Resume_Education_Honor_1_"]
                    }, {
                        "tag": "li",
                        "props": {},
                        "lang": "about",
                        "children": ["_aboutMe_Resume_Education_Honor_2_"]
                    }]
                }]
            }, {
                "tag": "div",
                "props": {
                    "class": "aboutMe_Resume_Session"
                },
                "lang": "",
                "children": [{
                    "tag": "p",
                    "props": {
                        "class": "aboutMe_Resume_Session_Title"
                    },
                    "lang": "about",
                    "children": ["_aboutMe_Resume_Projects_Personal_"]
                }, {
                    "tag": "div",
                    "props": {
                        "class": "aboutMe_Resume_Session_Projects"
                    },
                    "lang": "",
                    "children": [{
                        "tag": "p",
                        "props": {
                            "class": "aboutMe_Resume_Session_Projects_Title"
                        },
                        "lang": "",
                        "children": ["This is Title 2 这是一个标题 贰"]
                    }, {
                        "tag": "p",
                        "props": {
                            "class": "aboutMe_Resume_Session_Projects_Position"
                        },
                        "lang": "",
                        "children": ["My Position in this Projects"]
                    }, {
                        "tag": "p",
                        "props": {
                            "class": "aboutMe_Resume_Session_Projects_Time"
                        },
                        "lang": "",
                        "children": ["Jun 2024 - Aug 2025"]
                    }, {
                        "tag": "p",
                        "props": {
                            "class": "aboutMe_Resume_Session_Projects_Description"
                        }, 
                        "lang": "",
                        "children": ["descriptiondescriptiondescriptiondescription descriptiondescriptiondescriptiondescription descriptiondescriptiondescriptiondescription descriptiondescription descriptiondescriptiondescriptiondescription descriptiondescriptiondescriptiondescriptiondescriptiondescription   descriptiondescriptiondescriptiondescriptiondescriptiondescriptiondescriptiondescription descriptiondescription descriptiondescription"]
                    }, {
                        "tag": "p",
                        "props": {
                            "class": "aboutMe_Resume_Session_Projects_SecondTitle"
                        },
                        "lang": "",
                        "children": ["Implements Details"]
                    }, {
                        "tag": "div",
                        "props": {
                            "class": "aboutMe_Resume_Session_Projects_ImplDetails"
                        },
                        "lang": "",
                        "children": [{
                            "tag": "p",
                            "props": {},
                            "lang": "",
                            "children": ["Test is a test"]
                        }, {
                            "tag": "p",
                            "props": {},
                            "lang": "",
                            "children": ["This is a test"]
                        }]
                    }, {
                        "tag": "p",
                        "props": {
                            "class": "aboutMe_Resume_Session_Projects_SecondTitle"
                        },
                        "lang": "",
                        "children": ["Features 实现了什么"]
                    }, {
                        "tag": "ol",
                        "props": {},
                        "lang": "",
                        "children": [{
                            "tag": "li",
                            "props": {},
                            "lang": "",
                            "children": ["这是一个内容"]
                        }, {
                            "tag": "li",
                            "props": {},
                            "lang": "",
                            "children": ["This is a Content, Continue test content is not auto break, and the text position."]
                        }]
                    }, {
                        "tag": "p",
                        "props": {
                            "class": "aboutMe_Resume_Session_Projects_SecondTitle"
                        },
                        "lang": "",
                        "children": ["Key 学会了什么"]
                    }, {
                        "tag": "ol",
                        "props": {},
                        "lang": "",
                        "children": [{
                            "tag": "li",
                            "props": {},
                            "lang": "",
                            "children": ["这是一个内容"]
                        }, {
                            "tag": "li",
                            "props": {},
                            "lang": "",
                            "children": ["This is a Content, Continue test content is not auto break, and the text position."]
                        }]
                    }]
                }]
            }, {
                "tag": "div",
                "props": {
                    "class": "aboutMe_Resume_Session"
                },
                "lang": "",
                "children": [{
                    "tag": "p",
                    "props": {
                        "class": "aboutMe_Resume_Session_Title"
                    },
                    "lang": "about",
                    "children": ["_aboutMe_Resume_Projects_Graduation_"]
                }]
            }, {
                "tag": "div",
                "props": {
                    "class": "aboutMe_Resume_Session"
                },
                "lang": "",
                "children": [{
                    "tag": "p",
                    "props": {
                        "class": "aboutMe_Resume_Session_Title"
                    },
                    "lang": "about",
                    "children": ["_aboutMe_Resume_Projects_School_"]
                }]
            }]
        }] 
    }]
}, {
    "tag": "div",
    "props": {
        "id": "aboutMe_Resume_Download_Area"
    },
    "lang": "",
    "children": [{
        "tag": "p",
        "props": {
            "id": "aboutMe_Resume_Download_Button_PDF",
            "class": "aboutMe_Resume_Download_Button"
        },
        "lang": "about",
        "children": ["_aboutMe_Resume_Download_Button_PDF_"]
    }, {
        "tag": "p",
        "props": {
            "id": "aboutMe_Resume_Download_Button_DOCS",
            "class": "aboutMe_Resume_Download_Button"
        },
        "lang": "about",
        "children": ["_aboutMe_Resume_Download_Button_DOCS_"]
    }]
}]